troposphere_sugar
