Metadata-Version: 1.0
Name: troposphere-sugar
Version: 0.0.5
Summary: Common utilities on top of troposphere and boto for ease of clouformation template creation
Home-page: https://github.com/enriclluelles/troposphere_sugar
Author: Enric Lluelles
Author-email: enric@lluel.es
License: MIT
Platform: UNKNOWN
